nltpk/__init__.py
nltpk/loader.py
nltpk/data/Command.txt
nltpk/data/Map.txt
nltpk/data/N2.txt
nltpk/data/N3.txt
nltpk/data/N4.txt
nltpk/data/N5.txt
nltpk/data/N6.txt
nltpk-2.0.dist-info/METADATA
nltpk-2.0.dist-info/WHEEL
nltpk-2.0.dist-info/top_level.txt
nltpk-2.0.dist-info/RECORD
