Metadata-Version: 2.1
Name: nltpk
Version: 2.0
Summary: Saver
Author: Your Name
